.gitignore
LICENSE.txt
MANIFEST.in
README.md
pyproject.toml
src/nl.export.egg-info/PKG-INFO
src/nl.export.egg-info/SOURCES.txt
src/nl.export.egg-info/dependency_links.txt
src/nl.export.egg-info/entry_points.txt
src/nl.export.egg-info/requires.txt
src/nl.export.egg-info/top_level.txt
src/nl/export/__init__.py
src/nl/export/config.py
src/nl/export/errors.py
src/nl/export/gapi.py
src/nl/export/interfaces.py
src/nl/export/plone.py
src/nl/export/formatter/__init__.py
src/nl/export/formatter/csv.py
src/nl/export/formatter/json.py
src/nl/export/formatter/xml.py
src/nl/export/test/__init__.py
src/nl/export/tools/__init__.py
src/nl/export/tools/export/__init__.py
src/nl/export/tools/export/conf.py
src/nl/export/tools/export/lzn.py
src/nl/export/tools/export/proxy.py
src/nl/export/utils/__init__.py