Metadata-Version: 2.4
Name: nl.export
Version: 1.3.0
Summary: Einfaches Tool für den Zugriff auf ein NL-CMS
Author-email: "Marc-J. Tegethoff" <tegethoff@gbv.de>
License: GNU Affero General Public License v3
Project-URL: PyPI, https://pypi.python.org/pypi/nl.export
Project-URL: Source, https://github.com/gbv/nl.export
Project-URL: Tracker, https://github.com/gbv/nl.export/issues
Keywords: VZG,Python,Plone,Nationallizenzen
Classifier: Intended Audience :: Developers
Classifier: Programming Language :: Python
Classifier: Programming Language :: Python :: 3.12
Classifier: Programming Language :: Python :: 3.13
Classifier: Programming Language :: Python :: 3.14
Classifier: Operating System :: OS Independent
Classifier: License :: OSI Approved :: GNU Affero General Public License v3
Requires-Python: >=3.12
License-File: LICENSE.txt
Requires-Dist: lxml
Requires-Dist: requests
Requires-Dist: setuptools
Requires-Dist: tqdm
Requires-Dist: zope.interface
Dynamic: license-file
